{
  "generated_at": "2026-06-29T20:06:20.981611Z",
  "total_targets": 6788,
  "tier_histogram": {
    "HOT": 0,
    "WARM": 975,
    "COLD": 5813
  },
  "source_status": [
    {
      "slug": "directories.gbp_places+sba_foia+sba_foia",
      "name": "directories.gbp_places+sba_foia+sba_foia",
      "category": "email-crawl",
      "count": 6,
      "outcome": "OK",
      "reason": "website email crawl"
    },
    {
      "slug": "directories.gbp_places+sba_foia+licenses.nc_license_trades+sba_foia",
      "name": "directories.gbp_places+sba_foia+licenses.nc_license_trades+sba_foia",
      "category": "email-crawl",
      "count": 1,
      "outcome": "OK",
      "reason": "website email crawl"
    },
    {
      "slug": "licenses.nc_license_trades+sba_foia",
      "name": "licenses.nc_license_trades+sba_foia",
      "category": "email-crawl",
      "count": 1,
      "outcome": "OK",
      "reason": "website email crawl"
    },
    {
      "slug": "directories.gbp_places+licenses.nc_license_trades",
      "name": "directories.gbp_places+licenses.nc_license_trades",
      "category": "email-crawl",
      "count": 31,
      "outcome": "OK",
      "reason": "website email crawl"
    },
    {
      "slug": "licenses.nc_license_trades",
      "name": "licenses.nc_license_trades",
      "category": "email-crawl",
      "count": 479,
      "outcome": "OK",
      "reason": "website email crawl"
    },
    {
      "slug": "directories.yellowpages+licenses.nc_license_trades",
      "name": "directories.yellowpages+licenses.nc_license_trades",
      "category": "email-crawl",
      "count": 4,
      "outcome": "OK",
      "reason": "website email crawl"
    },
    {
      "slug": "directories.gbp_places+licenses.nc_license_trades+licenses.nclbgc+licenses.nclbgc",
      "name": "directories.gbp_places+licenses.nc_license_trades+licenses.nclbgc+licenses.nclbgc",
      "category": "email-crawl",
      "count": 1,
      "outcome": "OK",
      "reason": "website email crawl"
    },
    {
      "slug": "licenses.nc_license_trades+licenses.nclbgc+licenses.nclbgc",
      "name": "licenses.nc_license_trades+licenses.nclbgc+licenses.nclbgc",
      "category": "email-crawl",
      "count": 9,
      "outcome": "OK",
      "reason": "website email crawl"
    },
    {
      "slug": "licenses.nc_license_trades+licenses.nclbgc+licenses.nclbgc+licenses.nclbgc+licenses.nclbgc",
      "name": "licenses.nc_license_trades+licenses.nclbgc+licenses.nclbgc+licenses.nclbgc+licenses.nclbgc",
      "category": "email-crawl",
      "count": 2,
      "outcome": "OK",
      "reason": "website email crawl"
    },
    {
      "slug": "licenses.nc_license_trades+licenses.nclbgc",
      "name": "licenses.nc_license_trades+licenses.nclbgc",
      "category": "email-crawl",
      "count": 3,
      "outcome": "OK",
      "reason": "website email crawl"
    },
    {
      "slug": "licenses.nc_license_trades+licenses.nclbgc+licenses.nclbgc+licenses.nclbgc",
      "name": "licenses.nc_license_trades+licenses.nclbgc+licenses.nclbgc+licenses.nclbgc",
      "category": "email-crawl",
      "count": 1,
      "outcome": "OK",
      "reason": "website email crawl"
    },
    {
      "slug": "directories.gbp_places+licenses.nc_license_trades+directories.yellowpages",
      "name": "directories.gbp_places+licenses.nc_license_trades+directories.yellowpages",
      "category": "email-crawl",
      "count": 2,
      "outcome": "OK",
      "reason": "website email crawl"
    },
    {
      "slug": "directories.gbp_places+licenses.nc_license_trades+licenses.nclbgc",
      "name": "directories.gbp_places+licenses.nc_license_trades+licenses.nclbgc",
      "category": "email-crawl",
      "count": 1,
      "outcome": "OK",
      "reason": "website email crawl"
    },
    {
      "slug": "directories.gbp_places",
      "name": "directories.gbp_places",
      "category": "email-crawl",
      "count": 1375,
      "outcome": "OK",
      "reason": "website email crawl"
    },
    {
      "slug": "directories.gbp_places+directories.yellowpages",
      "name": "directories.gbp_places+directories.yellowpages",
      "category": "email-crawl",
      "count": 134,
      "outcome": "OK",
      "reason": "website email crawl"
    },
    {
      "slug": "directories.gbp_places+directories.yellowpages+directories.yellowpages",
      "name": "directories.gbp_places+directories.yellowpages+directories.yellowpages",
      "category": "email-crawl",
      "count": 8,
      "outcome": "OK",
      "reason": "website email crawl"
    },
    {
      "slug": "directories.gbp_places+directories.yellowpages+directories.yellowpages+directories.yellowpages",
      "name": "directories.gbp_places+directories.yellowpages+directories.yellowpages+directories.yellowpages",
      "category": "email-crawl",
      "count": 1,
      "outcome": "OK",
      "reason": "website email crawl"
    },
    {
      "slug": "directories.gbp_places+licenses.nclbgc+licenses.nclbgc",
      "name": "directories.gbp_places+licenses.nclbgc+licenses.nclbgc",
      "category": "email-crawl",
      "count": 1,
      "outcome": "OK",
      "reason": "website email crawl"
    },
    {
      "slug": "directories.gbp_places+licenses.nclbgc",
      "name": "directories.gbp_places+licenses.nclbgc",
      "category": "email-crawl",
      "count": 3,
      "outcome": "OK",
      "reason": "website email crawl"
    },
    {
      "slug": "directories.gbp_places+directories.yellowpages+licenses.nclbgc",
      "name": "directories.gbp_places+directories.yellowpages+licenses.nclbgc",
      "category": "email-crawl",
      "count": 1,
      "outcome": "OK",
      "reason": "website email crawl"
    },
    {
      "slug": "directories.yellowpages+sba_foia",
      "name": "directories.yellowpages+sba_foia",
      "category": "email-crawl",
      "count": 7,
      "outcome": "OK",
      "reason": "website email crawl"
    },
    {
      "slug": "directories.yellowpages+directories.yellowpages+sba_foia",
      "name": "directories.yellowpages+directories.yellowpages+sba_foia",
      "category": "email-crawl",
      "count": 1,
      "outcome": "OK",
      "reason": "website email crawl"
    },
    {
      "slug": "directories.yellowpages",
      "name": "directories.yellowpages",
      "category": "email-crawl",
      "count": 2577,
      "outcome": "OK",
      "reason": "website email crawl"
    },
    {
      "slug": "directories.yellowpages+licenses.nclbgc+licenses.nclbgc",
      "name": "directories.yellowpages+licenses.nclbgc+licenses.nclbgc",
      "category": "email-crawl",
      "count": 14,
      "outcome": "OK",
      "reason": "website email crawl"
    },
    {
      "slug": "directories.yellowpages+licenses.nclbgc",
      "name": "directories.yellowpages+licenses.nclbgc",
      "category": "email-crawl",
      "count": 3,
      "outcome": "OK",
      "reason": "website email crawl"
    },
    {
      "slug": "licenses.nclbgc+licenses.nclbgc+sba_foia",
      "name": "licenses.nclbgc+licenses.nclbgc+sba_foia",
      "category": "email-crawl",
      "count": 1,
      "outcome": "OK",
      "reason": "website email crawl"
    },
    {
      "slug": "licenses.nclbgc",
      "name": "licenses.nclbgc",
      "category": "email-crawl",
      "count": 449,
      "outcome": "OK",
      "reason": "website email crawl"
    },
    {
      "slug": "licenses.nclbgc+sba_foia",
      "name": "licenses.nclbgc+sba_foia",
      "category": "email-crawl",
      "count": 1,
      "outcome": "OK",
      "reason": "website email crawl"
    },
    {
      "slug": "marketplaces.craigslist_fsbo",
      "name": "marketplaces.craigslist_fsbo",
      "category": "email-crawl",
      "count": 8,
      "outcome": "OK",
      "reason": "website email crawl"
    },
    {
      "slug": "sba_foia",
      "name": "sba_foia",
      "category": "email-crawl",
      "count": 1663,
      "outcome": "OK",
      "reason": "website email crawl"
    }
  ]
}